azureml/__init__.py
azureml/ai/__init__.py
azureml/ai/monitoring/__init__.py
azureml/ai/monitoring/collector.py
azureml/ai/monitoring/collector_base.py
azureml/ai/monitoring/collector_json.py
azureml/ai/monitoring/init.py
azureml/ai/monitoring/common/__init__.py
azureml/ai/monitoring/config/__init__.py
azureml/ai/monitoring/config/config.py
azureml/ai/monitoring/context/__init__.py
azureml/ai/monitoring/context/context.py
azureml/ai/monitoring/logger/__init__.py
azureml/ai/monitoring/logger/logger.py
azureml/ai/monitoring/payload/__init__.py
azureml/ai/monitoring/payload/logdata.py
azureml/ai/monitoring/payload/payload.py
azureml/ai/monitoring/queue/__init__.py
azureml/ai/monitoring/queue/queue.py
azureml/ai/monitoring/worker/__init__.py
azureml/ai/monitoring/worker/sender.py
azureml/ai/monitoring/worker/worker.py
azureml_ai_monitoring-1.0.0.dist-info/METADATA
azureml_ai_monitoring-1.0.0.dist-info/WHEEL
azureml_ai_monitoring-1.0.0.dist-info/top_level.txt
azureml_ai_monitoring-1.0.0.dist-info/RECORD
