Metadata-Version: 2.1
Name: azureml-ai-monitoring
Version: 1.0.0
Summary: Microsoft Azure Machine Learning Python SDK v2 for collecting model data during operationalization
Author: Microsoft Corporation
Author-email: azuremlsdk@microsoft.com
License: MIT License
Keywords: AzureMachineLearning,ModelMonitoring
Platform: any
Classifier: Development Status :: 4 - Beta
Classifier: Intended Audience :: Developers
Classifier: Natural Language :: English
Classifier: Operating System :: OS Independent
Classifier: Programming Language :: Python
Classifier: Programming Language :: Python :: 3.7
Classifier: Programming Language :: Python :: 3.8
Classifier: Programming Language :: Python :: 3.9
Classifier: Programming Language :: Python :: 3.10
Classifier: License :: OSI Approved :: MIT License
Requires-Dist: pandas (>=1.5.2)
Requires-Dist: requests (>=2.28.1)
Provides-Extra: setup
Requires-Dist: setuptools (>=40.4.3) ; extra == 'setup'
Requires-Dist: pip (~=20.3) ; extra == 'setup'
Requires-Dist: wheel ; extra == 'setup'
Provides-Extra: test
Requires-Dist: pytest-subtests ; extra == 'test'
Requires-Dist: pytest-cov ; extra == 'test'
Requires-Dist: pytest-xdist ; extra == 'test'
Requires-Dist: numpy ; extra == 'test'
Requires-Dist: pandas ; extra == 'test'
